foodAlertsAPI/Alert.py
foodAlertsAPI/Allergen.py
foodAlertsAPI/BatchDescription.py
foodAlertsAPI/Business.py
foodAlertsAPI/Country.py
foodAlertsAPI/HazardCategory.py
foodAlertsAPI/PathogenRisk.py
foodAlertsAPI/Problem.py
foodAlertsAPI/ProductCategory.py
foodAlertsAPI/ProductDetails.py
foodAlertsAPI/Reason.py
foodAlertsAPI/RelatedMedia.py
foodAlertsAPI/Status.py
foodAlertsAPI/__init__.py
foodAlertsAPI/foodAlertsAPI.py
food_alerts_wrapper-0.1.1.dist-info/LICENSE
food_alerts_wrapper-0.1.1.dist-info/METADATA
food_alerts_wrapper-0.1.1.dist-info/WHEEL
food_alerts_wrapper-0.1.1.dist-info/top_level.txt
food_alerts_wrapper-0.1.1.dist-info/RECORD
