Metadata-Version: 2.1
Name: food-alerts-wrapper
Version: 0.1.1
Summary: A python wrapper for the FSA food alerts API
Home-page: https://github.com/epimorphics/food-alerts-wrapper
Author: Adrian David
Author-email: adrian.david@epimorphics.com
License: UNKNOWN
Platform: UNKNOWN
Classifier: Programming Language :: Python :: 3
Classifier: License :: OSI Approved :: MIT License
Classifier: Operating System :: OS Independent
Requires-Python: >=3
Requires-Dist: requests
